overcluster/__init__.py
overcluster/bisect_q_means.py
overcluster/utils.py
overcluster-0.1.3.dist-info/LICENSE
overcluster-0.1.3.dist-info/METADATA
overcluster-0.1.3.dist-info/WHEEL
overcluster-0.1.3.dist-info/top_level.txt
overcluster-0.1.3.dist-info/RECORD
