Metadata-Version: 2.1
Name: overcluster
Version: 0.1.3
Summary: Expanding cluster membership to include neighbors
Author: Shane Grigsby
Author-email: refuge@rocktalus.com
License: BSD 3-Clause License
Keywords: clustering
Classifier: Programming Language :: Python :: 3
Classifier: License :: OSI Approved :: BSD License
Classifier: Operating System :: OS Independent
Requires-Python: >=3.6
License-File: LICENSE
Requires-Dist: tqdm
